vvclasses/__init__.py
vvclasses/__main__.py
vvclasses/main.py
vvclasses/src/__init__.py
vvclasses/src/pf.py
vvclasses/tests/example_using_prints.py
vvclasses/utils/__init__.py
vvclasses/utils/printclass.py
vvclasses-0.0.9.dist-info/METADATA
vvclasses-0.0.9.dist-info/WHEEL
vvclasses-0.0.9.dist-info/entry_points.txt
vvclasses-0.0.9.dist-info/top_level.txt
vvclasses-0.0.9.dist-info/RECORD
