Metadata-Version: 2.1
Name: vvclasses
Version: 0.0.9
Summary: Some classes that im going to use for other apps
Home-page: https://github.com/yourusername/your-repo.git
Author: vince
Author-email: vince <your_email@example.com>
License: MIT
Project-URL: Homepage, https://github.com/VinnyVanGogh/VinnyVanGoghClasses.git
Requires-Python: >=3.10
Requires-Dist: colorama>=0.4.6
Requires-Dist: pygments>=2.10.0
